[
    {
        "model": "levelupapi.event",
        "pk": 1,
        "fields": {
            "description": "life players unite",
            "date": "2022-02-05",
            "time": "5:00",
            "game_id": 1,
            "organizer_id": 1
        }
    },
    {
        "model": "levelupapi.event",
        "pk": 2,
        "fields": {
            "description": "blues Clues",
            "date": "2022-02-10",
            "time": "7:00",
            "game_id": 1,
            "organizer_id": 1
        }
    }
]